SIRemote/HttpCommunicationUtil.py
SIRemote/RemoteApi.py
SIRemote/__init__.py
apps/RemoteInteractionDemo.py
apps/__init__.py
siremote-1.1.1.dist-info/METADATA
siremote-1.1.1.dist-info/WHEEL
siremote-1.1.1.dist-info/entry_points.txt
siremote-1.1.1.dist-info/top_level.txt
siremote-1.1.1.dist-info/RECORD
