Metadata-Version: 2.4
Name: SIRemote
Version: 1.1.1
Summary: API for remote interaction with the Ninox360 Surface Inspector 3D scanner
Author-email: Maxim Dossioukov <support@ninox360.com>
License: Apache-2.0
Project-URL: Homepage, https://github.com/NINOX-360/Surface-Inspector-Remote
Project-URL: Issues, https://github.com/NINOX-360/Surface-Inspector-Remote/issues
Classifier: Programming Language :: Python :: 3
Classifier: Operating System :: OS Independent
Requires-Python: >=3.6
Requires-Dist: requests
Requires-Dist: PyYAML
Requires-Dist: Pillow
